nomad_camels_driver_demo_digital_multimeter/demo_digital_multimeter.py
nomad_camels_driver_demo_digital_multimeter/demo_digital_multimeter_ophyd.py
nomad_camels_driver_demo_digital_multimeter-0.1.4.dist-info/licenses/LICENSE.txt
nomad_camels_driver_demo_digital_multimeter-0.1.4.dist-info/METADATA
nomad_camels_driver_demo_digital_multimeter-0.1.4.dist-info/WHEEL
nomad_camels_driver_demo_digital_multimeter-0.1.4.dist-info/top_level.txt
nomad_camels_driver_demo_digital_multimeter-0.1.4.dist-info/RECORD
